business_rules/__init__.py
business_rules/actions.py
business_rules/engine.py
business_rules/fields.py
business_rules/operators.py
business_rules/six.py
business_rules/utils.py
business_rules/variables.py
business_rules_devlibx-0.0.8.dist-info/LICENSE
business_rules_devlibx-0.0.8.dist-info/METADATA
business_rules_devlibx-0.0.8.dist-info/WHEEL
business_rules_devlibx-0.0.8.dist-info/top_level.txt
business_rules_devlibx-0.0.8.dist-info/RECORD
